decentro_in_collections_client/__init__.py
decentro_in_collections_client/api_client.py
decentro_in_collections_client/api_response.py
decentro_in_collections_client/apis/__init__.py
decentro_in_collections_client/apis/path_to_api.py
decentro_in_collections_client/apis/paths/__init__.py
decentro_in_collections_client/apis/paths/v2_payments_collection.py
decentro_in_collections_client/apis/paths/v2_payments_transaction_transaction_id_status.py
decentro_in_collections_client/apis/paths/v2_payments_upi_link.py
decentro_in_collections_client/apis/paths/v2_payments_upi_refund.py
decentro_in_collections_client/apis/paths/v2_payments_vpa_validate.py
decentro_in_collections_client/apis/tag_to_api.py
decentro_in_collections_client/client.py
decentro_in_collections_client/client.pyi
decentro_in_collections_client/client_custom.py
decentro_in_collections_client/configuration.py
decentro_in_collections_client/exceptions.py
decentro_in_collections_client/exceptions_base.py
decentro_in_collections_client/model/__init__.py
decentro_in_collections_client/model/generate_payment_link400_response.py
decentro_in_collections_client/model/generate_payment_link400_response.pyi
decentro_in_collections_client/model/generate_payment_link_request.py
decentro_in_collections_client/model/generate_payment_link_request.pyi
decentro_in_collections_client/model/generate_payment_link_response.py
decentro_in_collections_client/model/generate_payment_link_response.pyi
decentro_in_collections_client/model/generate_payment_link_response_data.py
decentro_in_collections_client/model/generate_payment_link_response_data.pyi
decentro_in_collections_client/model/generate_payment_link_response_data_psp_uri.py
decentro_in_collections_client/model/generate_payment_link_response_data_psp_uri.pyi
decentro_in_collections_client/model/get_transaction_status_response.py
decentro_in_collections_client/model/get_transaction_status_response.pyi
decentro_in_collections_python_sdk-1.0.0.dist-info/LICENSE
decentro_in_collections_python_sdk-1.0.0.dist-info/METADATA
decentro_in_collections_python_sdk-1.0.0.dist-info/WHEEL
decentro_in_collections_python_sdk-1.0.0.dist-info/RECORD
